poetry_codeartifact_plugin/__init__.py
poetry_codeartifact_plugin/plugin.py
poetry_codeartifact_plugin-1.0.3.dist-info/LICENSE
poetry_codeartifact_plugin-1.0.3.dist-info/METADATA
poetry_codeartifact_plugin-1.0.3.dist-info/WHEEL
poetry_codeartifact_plugin-1.0.3.dist-info/entry_points.txt
poetry_codeartifact_plugin-1.0.3.dist-info/RECORD
