Metadata-Version: 2.1
Name: poetry-codeartifact-plugin
Version: 1.0.3
Summary: A poetry plugin for keeping your CodeArtifact authorization token up-to-date
Author: Tom Petr
Author-email: tom@r2c.dev
Requires-Python: >=3.8,<4.0
Classifier: Programming Language :: Python :: 3
Classifier: Programming Language :: Python :: 3.8
Classifier: Programming Language :: Python :: 3.9
Classifier: Programming Language :: Python :: 3.10
Classifier: Programming Language :: Python :: 3.11
Classifier: Programming Language :: Python :: 3.12
Requires-Dist: boto3 (>=1.24.57,<2.0.0)
Requires-Dist: poetry (>=1.2.0,<2.0.0)
